setup.py
ppp_questionparsing_grammatical/__init__.py
ppp_questionparsing_grammatical/config.py
ppp_questionparsing_grammatical/dependencyAnalysis.py
ppp_questionparsing_grammatical/dependencyTree.py
ppp_questionparsing_grammatical/initialMerge.py
ppp_questionparsing_grammatical/normalization.py
ppp_questionparsing_grammatical/nounDB.py
ppp_questionparsing_grammatical/preprocessing.py
ppp_questionparsing_grammatical/questionWordProcessing.py
ppp_questionparsing_grammatical/requesthandler.py
ppp_questionparsing_grammatical.egg-info/PKG-INFO
ppp_questionparsing_grammatical.egg-info/SOURCES.txt
ppp_questionparsing_grammatical.egg-info/dependency_links.txt
ppp_questionparsing_grammatical.egg-info/requires.txt
ppp_questionparsing_grammatical.egg-info/top_level.txt
ppp_questionparsing_grammatical/data/__init__.py
ppp_questionparsing_grammatical/data/__pycache__
ppp_questionparsing_grammatical/data/conjunction.py
ppp_questionparsing_grammatical/data/exceptions.py
ppp_questionparsing_grammatical/data/nounificationAuto.pickle
ppp_questionparsing_grammatical/data/nounificationManual.txt
ppp_questionparsing_grammatical/data/pastParticiple.pickle
ppp_questionparsing_grammatical/data/questionWord.py
ppp_questionparsing_grammatical/data/superlative.py