Metadata-Version: 1.1
Name: ppp-questionparsing-grammatical
Version: 0.6.5
Summary: Natural language processing module for the PPP.
Home-page: https://github.com/ProjetPP/PPP-QuestionParsing-Grammatical
Author: Projet Pensées Profondes
Author-email: ppp2014@listes.ens-lyon.fr
License: MIT
Platform: UNKNOWN
Classifier: Environment :: No Input/Output (Daemon)
Classifier: Development Status :: 1 - Planning
Classifier: Intended Audience :: System Administrators
Classifier: License :: OSI Approved :: MIT License
Classifier: Natural Language :: English
Classifier: Operating System :: OS Independent
Classifier: Programming Language :: Python :: 3
Classifier: Programming Language :: Python :: 3.2
Classifier: Programming Language :: Python :: 3.3
Classifier: Programming Language :: Python :: 3.4
Classifier: Topic :: Internet :: WWW/HTTP :: WSGI :: Application
Classifier: Topic :: Software Development :: Libraries
